foundry/__init__.py
foundry/_core/__init__.py
foundry/_core/api_client.py
foundry/_core/auth_utils.py
foundry/_core/binary_stream.py
foundry/_core/confidential_client_auth.py
foundry/_core/config.py
foundry/_core/foundry_token_auth_client.py
foundry/_core/oauth.py
foundry/_core/oauth_utils.py
foundry/_core/page_iterator.py
foundry/_core/public_client_auth.py
foundry/_core/resource_iterator.py
foundry/_core/utils.py
foundry/_errors/__init__.py
foundry/_errors/connection_error.py
foundry/_errors/environment_not_configured.py
foundry/_errors/not_authenticated.py
foundry/_errors/palantir_exception.py
foundry/_errors/palantir_rpc_exception.py
foundry/_errors/sdk_internal_error.py
foundry/_errors/stream_error.py
foundry/_errors/timeout_error.py
foundry/_errors/utils.py
foundry/_versions.py
foundry/py.typed
foundry/v1/__init__.py
foundry/v1/cli.py
foundry/v1/client.py
foundry/v1/core/errors/__init__.py
foundry/v1/core/errors/_api_feature_preview_usage_only.py
foundry/v1/core/errors/_api_usage_denied.py
foundry/v1/core/errors/_folder_not_found.py
foundry/v1/core/errors/_invalid_page_size.py
foundry/v1/core/errors/_invalid_page_token.py
foundry/v1/core/errors/_invalid_parameter_combination.py
foundry/v1/core/errors/_missing_post_body.py
foundry/v1/core/errors/_resource_name_already_exists.py
foundry/v1/core/errors/_unknown_distance_unit.py
foundry/v1/core/models/__init__.py
foundry/v1/core/models/_any_type.py
foundry/v1/core/models/_any_type_dict.py
foundry/v1/core/models/_attachment_type_dict.py
foundry/v1/core/models/_binary_type.py
foundry/v1/core/models/_binary_type_dict.py
foundry/v1/core/models/_boolean_type.py
foundry/v1/core/models/_boolean_type_dict.py
foundry/v1/core/models/_byte_type.py
foundry/v1/core/models/_byte_type_dict.py
foundry/v1/core/models/_cipher_text_type.py
foundry/v1/core/models/_cipher_text_type_dict.py
foundry/v1/core/models/_date_type.py
foundry/v1/core/models/_date_type_dict.py
foundry/v1/core/models/_decimal_type.py
foundry_platform_sdk-0.70.0.dist-info/LICENSE
foundry_platform_sdk-0.70.0.dist-info/METADATA
foundry_platform_sdk-0.70.0.dist-info/WHEEL
foundry_platform_sdk-0.70.0.dist-info/entry_points.txt
foundry_platform_sdk-0.70.0.dist-info/RECORD
