Metadata-Version: 2.1
Name: foundry-platform-sdk
Version: 0.70.0
Summary: The official Python library for the Foundry API
Home-page: https://github.com/palantir/foundry-platform-python
License: Apache-2.0
Keywords: Palantir,Foundry,SDK,Client,API
Author: Palantir Technologies, Inc.
Requires-Python: >=3.9,<4.0
Classifier: License :: OSI Approved :: Apache Software License
Classifier: Programming Language :: Python :: 3
Classifier: Programming Language :: Python :: 3.9
Classifier: Programming Language :: Python :: 3.10
Classifier: Programming Language :: Python :: 3.11
Classifier: Programming Language :: Python :: 3.12
Classifier: Programming Language :: Python :: 3.13
Provides-Extra: cli
Requires-Dist: annotated-types (>=0.7.0,<1.0.0)
Requires-Dist: httpx (>=0.24.0,<1.0.0)
Requires-Dist: pydantic (>=2.1.0,<3.0.0)
Requires-Dist: typing-extensions (>=4.7.1,<5.0.0)
Project-URL: Repository, https://github.com/palantir/foundry-platform-python
